wg_node_client-0.1.0.dist-info/METADATA
wg_node_client-0.1.0.dist-info/WHEEL
wg_node_client-0.1.0.dist-info/licenses/LICENSE
wg_node_client/__init__.py
wg_node_client/wg_node_client.py
wg_node_client-0.1.0.dist-info/RECORD
